README.txt
setup.py
BAndroidDriver/BAndroidDriver.py
BAndroidDriver/BApp.py
BAndroidDriver/BElement.py
BAndroidDriver/BEmail.py
BAndroidDriver/BFile.py
BAndroidDriver/BLog.py
BAndroidDriver/Bjson.py
BAndroidDriver/GetLog.py
BAndroidDriver/__init__.py
BAndroidDriver.egg-info/PKG-INFO
BAndroidDriver.egg-info/SOURCES.txt
BAndroidDriver.egg-info/dependency_links.txt
BAndroidDriver.egg-info/top_level.txt
BAndroidDriver.egg-info/zip-safe