Metadata-Version: 1.1
Name: BAndroidDriver
Version: 1.0.3
Summary: this is a test package for packing python liberaries tutorial.
Home-page: https://my.oschina.net/hibony/blog
Author: MitchellChu
Author-email: boyne@foxmail.com
License: MIT
Keywords: test python package
Platform: UNKNOWN
Classifier: License :: OSI Approved :: MIT License
Classifier: Programming Language :: Python
Classifier: Intended Audience :: Developers
Classifier: Operating System :: OS Independent
